{
    "@context": "https://schema.org",
    "@type": "Organization",
    "address": {
        "@type": "PostalAddress",
        "postalCode": {
            "value": "17-200",
            "trueValue": "17-200",
            "elemId": [
                "word_1_35"
            ]
        },
        "streetAddress": {
            "value": "ul. 3 Maja 54",
            "trueValue": "ul. 3 Maja 54",
            "elemId": [
                "word_1_30",
                "word_1_31",
                "word_1_32",
                "word_1_33"
            ]
        },
        "addressLocality": {
            "value": "Hajnówka",
            "trueValue": "Hajnówka",
            "elemId": [
                "word_1_36"
            ]
        }
    },
    "name": {
        "value": "SZKOŁA PODSTAWOWA NR 1 IM. JANUSZA KUSOCIŃSKIEGO W HAJNÓWCE",
        "trueValue": "SZKOŁA PODSTAWOWA NR 1 IM. JANUSZA KUSOCIŃSKIEGO W HAJNÓWCE",
        "elemId": [
            "word_1_3",
            "word_1_4",
            "word_1_5",
            "word_1_6",
            "word_1_7",
            "word_1_8",
            "word_1_9",
            "word_1_10",
            "word_1_11"
        ]
    },
    "foundingDate": {
        "value": "1959-09-01",
        "trueValue": "1959-09-01",
        "elemId": [
            "word_1_34"
        ]
    },
    "regon": {
        "value": "001037123",
        "trueValue": "001037123",
        "elemId": [
            "word_1_13"
        ]
    },
    "email": {
        "value": "spihajnowkaQwp.pl",
        "trueValue": "sp1hajnowka@wp.pl",
        "elemId": [
            "word_1_41"
        ]
    },
    "telephone": {
        "value": "856 822 078",
        "trueValue": "856 822 078",
        "elemId": [
            "word_1_43",
            "word_1_44",
            "word_1_45"
        ]
    }
}