{
    "@context": "https://schema.org",
    "@type": "Organization",
    "address": {
        "@type": "PostalAddress",
        "postalCode": {
            "value": "15-063",
            "trueValue": "15-063",
            "elemId": [
                "word_1_33"
            ]
        },
        "streetAddress": {
            "value": "ul. Warszawska 2",
            "trueValue": "ul. Warszawska 2",
            "elemId": [
                "word_1_29",
                "word_1_30",
                "word_1_31"
            ]
        },
        "addressLocality": {
            "value": "Białystok",
            "trueValue": "Białystok",
            "elemId": [
                "word_1_34"
            ]
        }
    },
    "name": {
        "value": "POLICEALNA SZKOŁA TOWARZYSTWA WIEDZY POWSZECHNEJ W BIAŁYMSTOKU",
        "trueValue": "POLICEALNA SZKOŁA TOWARZYSTWA WIEDZY POWSZECHNEJ W BIAŁYMSTOKU",
        "elemId": [
            "word_1_3",
            "word_1_4",
            "word_1_5",
            "word_1_6",
            "word_1_7",
            "word_1_8",
            "word_1_9"
        ]
    },
    "foundingDate": {
        "value": "1995-05-27",
        "trueValue": "1995-05-27",
        "elemId": [
            "word_1_41"
        ]
    },
    "regon": {
        "value": "200778532",
        "trueValue": "200778532",
        "elemId": [
            "word_1_45"
        ]
    },
    "email": {
        "value": "naukaGtwp.bialystok.pl",
        "trueValue": "nauka@twp.bialystok.pl",
        "elemId": [
            "word_1_19"
        ]
    },
    "telephone": {
        "value": "857 435 106",
        "trueValue": "857 435 106",
        "elemId": [
            "word_1_38",
            "word_1_39",
            "word_1_40"
        ]
    }
}